pyqbdi.cpython-312-x86_64-linux-gnu.so
pyqbdipreload.py
pyqbdipreloadlib.cpython-312-x86_64-linux-gnu.so
pyqbdi-0.12.1.dist-info/METADATA
pyqbdi-0.12.1.dist-info/WHEEL
pyqbdi-0.12.1.dist-info/top_level.txt
pyqbdi-0.12.1.dist-info/RECORD
pyqbdi-0.12.1.dist-info/licenses/LICENSE.txt
