Metadata-Version: 2.1
Name: PyQBDI
Version: 0.12.1
Summary: Python binding for QBDI
Author: Nicolas Surbayrole
Author-email: qbdi@quarkslab.com
License: apache2
Project-URL: Documentation, https://qbdi.readthedocs.io/
Project-URL: Source, https://github.com/QBDI/QBDI
Project-URL: Homepage, https://qbdi.quarkslab.com/
Classifier: Development Status :: 5 - Production/Stable
Classifier: Operating System :: Microsoft :: Windows
Classifier: Operating System :: MacOS
Classifier: Operating System :: POSIX :: Linux
Classifier: Programming Language :: C++
Classifier: Programming Language :: Python :: 3.8
Classifier: Programming Language :: Python :: 3.9
Classifier: Programming Language :: Python :: 3.10
Classifier: Programming Language :: Python :: 3.11
Classifier: Programming Language :: Python :: 3.12
Classifier: Programming Language :: Python :: 3.13
Classifier: Programming Language :: Python :: 3.14
Classifier: Topic :: Security
Classifier: Topic :: Software Development :: Debuggers
Requires-Python: >=3.8
License-File: LICENSE.txt
